/**
 * COPYRIGHT (C) ENZO
 * OFICIAL FONT / OFFICIAL LANGUAGE MAP
 */

<dictionary>
    <comment>No copy code</comment>

    <entry id="1">
        <word>OIA</word>
        <meaning>olá</meaning>
    </entry>

    <entry id="2">
        <word>FRANCIES</word>
        <meaning>pessoa, pessoas, pessoal</meaning>
    </entry>

    <entry id="3">
        <word>FRATCIÄSŌ</word>
        <meaning>os, as, o, a</meaning>
    </entry>

    <entry id="4">
        <word>FÂZKOÖËD</word>
        <meaning>mer$@, mer@@$, coc@</meaning>
    </entry>

    <entry id="5">
        <word>KOKÔFAZLOSIÄ</word>
        <meaning>oi, teste, testando, testa, testes</meaning>
    </entry>

    <entry id="6">
        <word>KOHOFÅÇÕÄ</word>
        <meaning>nome, nomes, noma, nome</meaning>
    </entry>
</dictionary>
